CHANGES.rst
MANIFEST.in
README.rst
base.cfg
bootstrap.py
buildout.cfg
checkouts.cfg
setup.py
sources.cfg
travis.cfg
versions.cfg
Products/__init__.py
Products.PloneGazette.egg-info/PKG-INFO
Products.PloneGazette.egg-info/SOURCES.txt
Products.PloneGazette.egg-info/dependency_links.txt
Products.PloneGazette.egg-info/entry_points.txt
Products.PloneGazette.egg-info/namespace_packages.txt
Products.PloneGazette.egg-info/not-zip-safe
Products.PloneGazette.egg-info/pbr.json
Products.PloneGazette.egg-info/requires.txt
Products.PloneGazette.egg-info/top_level.txt
Products/PloneGazette/Newsletter.py
Products/PloneGazette/NewsletterBTree.py
Products/PloneGazette/NewsletterReference.py
Products/PloneGazette/NewsletterRichReference.py
Products/PloneGazette/NewsletterTheme.py
Products/PloneGazette/NewsletterTopic.py
Products/PloneGazette/PNLBase.py
Products/PloneGazette/PNLPermissions.py
Products/PloneGazette/PNLUtils.py
Products/PloneGazette/README.txt
Products/PloneGazette/Section.py
Products/PloneGazette/Subscriber.py
Products/PloneGazette/__init__.py
Products/PloneGazette/adapters.py
Products/PloneGazette/adapters.zcml
Products/PloneGazette/catalog.py
Products/PloneGazette/config.py
Products/PloneGazette/configure.zcml
Products/PloneGazette/interfaces.py
Products/PloneGazette/migration.py
Products/PloneGazette/patches.py
Products/PloneGazette/roadmap.txt
Products/PloneGazette/setuphandlers.py
Products/PloneGazette/skins.zcml
Products/PloneGazette/upgrades.py
Products/PloneGazette/upgrades.zcml
Products/PloneGazette/version.txt
Products/PloneGazette/Extensions/Install.py
Products/PloneGazette/browser/__init__.py
Products/PloneGazette/browser/configure.zcml
Products/PloneGazette/browser/interfaces.py
Products/PloneGazette/browser/miscellaneous.py
Products/PloneGazette/browser/newsletterbtree.py
Products/PloneGazette/browser/stylesheets/style.css
Products/PloneGazette/browser/templates/newsletterbtree_view.pt
Products/PloneGazette/docs/CONTRIBUTORS.rst
Products/PloneGazette/docs/CREDITS.rst
Products/PloneGazette/docs/INSTALL.rst
Products/PloneGazette/docs/LICENSE.rst
Products/PloneGazette/docs/Makefile
Products/PloneGazette/docs/README.rst
Products/PloneGazette/docs/TODO.rst
Products/PloneGazette/docs/UPGRADE.rst
Products/PloneGazette/docs/conf.py
Products/PloneGazette/docs/index.rst
Products/PloneGazette/docs/_static/.gitignore
Products/PloneGazette/locales/manual.pot
