Metadata-Version: 1.1
Name: Products.PloneGazette
Version: 3.2.5
Summary: A complete Newsletter product for Plone.
Home-page: http://plone.org/products/plonegazette
Author: Morten W. Petersen
Author-email: info@nidelven-it.no
License: UNKNOWN
Keywords: Zope plone newsletter communication
Platform: UNKNOWN
Classifier: Framework :: Plone
Classifier: Framework :: Plone :: 4.2
Classifier: Framework :: Plone :: 4.3
Classifier: Programming Language :: Python
Classifier: Programming Language :: Python :: 2.7
